<?xml version="1.0" encoding="UTF-8" standalone="yes"?>



<item> 
<title>[COLOR yellow]_**_ [/COLOR][COLOR  skyblue] SERIES [/COLOR][COLOR yellow] _**_[/COLOR]</title>
<link>http://Ignoreme</link>
<thumbnail></thumbnail>
<fanart></fanart>
<externallink></externallink>	
</item> 


<item> 
<title>[COLOR yellow]_**_ [/COLOR][COLOR  skyblue] SERIES RETRO [/COLOR][COLOR yellow] _**_[/COLOR]</title>
<link>http://Ignoreme</link>
<thumbnail></thumbnail>
<fanart></fanart>
<externallink></externallink>	
</item> 


<item> 
<title>[COLOR yellow]_**_ [/COLOR][COLOR  skyblue] SERIES A-Z[/COLOR][COLOR yellow] _**_[/COLOR]</title>
<link>http://Ignoreme</link>
<thumbnail>http://i.imgur.com/Sy34OJp.jpg</thumbnail>
<fanart>http://i.imgur.com/Sy34OJp.jpg</fanart>
<externallink>https://raw.githubusercontent.com/lokiyotnt69/JHG.MASTER.3.0/master/SERIESJHG3.xml</externallink>	
</item> 

<item> 
<title>[COLOR yellow]_**_ [/COLOR][COLOR  skyblue]  [/COLOR][COLOR yellow] _**_[/COLOR]</title>
<link>http://Ignoreme</link>
<thumbnail></thumbnail>
<fanart></fanart>
<externallink></externallink>	
</item> 